CHANGES.txt
LICENCES.txt
bootstrap.py
buildout.cfg
setup.py
flash/fla/debug.as
flash/fla/upload.fla
flash/src/z3c/widget/flashupload/baseskin/ScrollBox.as
flash/src/z3c/widget/flashupload/baseskin/Upload.as
src/z3c/__init__.py
src/z3c.widget.egg-info/PKG-INFO
src/z3c.widget.egg-info/SOURCES.txt
src/z3c.widget.egg-info/dependency_links.txt
src/z3c.widget.egg-info/namespace_packages.txt
src/z3c.widget.egg-info/not-zip-safe
src/z3c.widget.egg-info/requires.txt
src/z3c.widget.egg-info/top_level.txt
src/z3c/widget/__init__.py
src/z3c/widget/autocomplete/README.txt
src/z3c/widget/autocomplete/__init__.py
src/z3c/widget/autocomplete/configure.zcml
src/z3c/widget/autocomplete/ftesting.zcml
src/z3c/widget/autocomplete/ftests.py
src/z3c/widget/autocomplete/interfaces.py
src/z3c/widget/autocomplete/suggestions.pt
src/z3c/widget/autocomplete/tests.py
src/z3c/widget/autocomplete/widget.py
src/z3c/widget/autocomplete/z3c.widget.autocomplete-configure.zcml
src/z3c/widget/autocomplete/demo/README.txt
src/z3c/widget/autocomplete/demo/__init__.py
src/z3c/widget/autocomplete/demo/browser.py
src/z3c/widget/autocomplete/demo/configure.zcml
src/z3c/widget/autocomplete/demo/content.py
src/z3c/widget/autocomplete/demo/countries.py
src/z3c/widget/autocomplete/demo/interfaces.py
src/z3c/widget/autocomplete/demo/tests.py
src/z3c/widget/autocomplete/demo/z3c.widget.autocomplete.demo-configure.zcml
src/z3c/widget/country/DEPENDENCIES.cfg
src/z3c/widget/country/README.txt
src/z3c/widget/country/SETUP.cfg
src/z3c/widget/country/__init__.py
src/z3c/widget/country/configure.zcml
src/z3c/widget/country/tests.py
src/z3c/widget/country/widget.py
src/z3c/widget/country/z3c.widget.country-configure.zcml
src/z3c/widget/dateselect/README.txt
src/z3c/widget/dateselect/__init__.py
src/z3c/widget/dateselect/browser.py
src/z3c/widget/dateselect/configure.zcml
src/z3c/widget/dateselect/testing.py
src/z3c/widget/dateselect/tests.py
src/z3c/widget/dateselect/widget-date.pt
src/z3c/widget/dropdowndatewidget/README.txt
src/z3c/widget/dropdowndatewidget/__init__.py
src/z3c/widget/dropdowndatewidget/overrides.zcml
src/z3c/widget/dropdowndatewidget/tests.py
src/z3c/widget/dropdowndatewidget/widget.py
src/z3c/widget/dropdowndatewidget/z3c.widget.dropdowndatewidget-overrides.zcml
