Metadata-Version: 1.0
Name: z3c.widget
Version: 0.3.0
Summary: Additional zope.formlib Widgets
Home-page: http://svn.zope.org/z3c.widget
Author: Zope Community
Author-email: zope-dev@zope.org
License: ZPL 2.1
Keywords: zope zope3 form formlib
Platform: UNKNOWN
Classifier: Development Status :: 4 - Beta
Classifier: Environment :: Web Environment
Classifier: Framework :: Zope3
Classifier: Intended Audience :: Developers
Classifier: License :: OSI Approved :: Zope Public License
Classifier: License :: OSI Approved :: GNU Library or Lesser General Public License (LGPL)
Classifier: Programming Language :: Python
Classifier: Topic :: Software Development :: Libraries :: Python Modules
